geotrees/__init__.py
geotrees/distance_metrics.py
geotrees/great_circle.py
geotrees/kdtree.py
geotrees/neighbours.py
geotrees/octtree.py
geotrees/quadtree.py
geotrees/record.py
geotrees/shape.py
geotrees/utils.py
geotrees-1.1.0.dist-info/METADATA
geotrees-1.1.0.dist-info/WHEEL
geotrees-1.1.0.dist-info/licenses/LICENSE
geotrees-1.1.0.dist-info/RECORD
