Metadata-Version: 2.4
Name: geotrees
Version: 1.1.0
Summary: QuadTree and KDTree implementation on a spherical Earth
Project-URL: Homepage, https://github.com/NOCSurfaceProcesses/geotrees
Project-URL: Source, https://github.com/NOCSurfaceProcesses/geotrees
Project-URL: Issue tracker, https://github.com/NOCSurfaceProcesses/geotrees/issues
Author-email: Joseph Siddons <josidd@noc.ac.uk>, Richard Cornes <rcornes@noc.ac.uk>
Maintainer-email: Joseph Siddons <josidd@noc.ac.uk>
License-File: LICENSE
Keywords: geospatial,haversine,kdtree,nearest neighbour,octtree,quadtree,spatial,spherical,trees
Classifier: Development Status :: 5 - Production/Stable
Classifier: Intended Audience :: Science/Research
Classifier: License :: OSI Approved :: Apache Software License
Classifier: Operating System :: OS Independent
Classifier: Programming Language :: Python :: 3.9
Classifier: Programming Language :: Python :: 3.10
Classifier: Programming Language :: Python :: 3.11
Classifier: Programming Language :: Python :: 3.12
Classifier: Programming Language :: Python :: 3.13
Classifier: Programming Language :: Python :: 3.14
Requires-Python: >=3.9
Requires-Dist: numpy
Provides-Extra: all
Requires-Dist: ipykernel; extra == 'all'
Requires-Dist: polars; extra == 'all'
Requires-Dist: pytest; extra == 'all'
Requires-Dist: pytest-cov>=6.1.1; extra == 'all'
Requires-Dist: sphinx; extra == 'all'
Requires-Dist: sphinx-autodoc-typehints; extra == 'all'
Requires-Dist: sphinx-rtd-theme; extra == 'all'
Provides-Extra: docs
Requires-Dist: sphinx; extra == 'docs'
Requires-Dist: sphinx-autodoc-typehints; extra == 'docs'
Requires-Dist: sphinx-rtd-theme; extra == 'docs'
Provides-Extra: notebooks
Requires-Dist: ipykernel; extra == 'notebooks'
Requires-Dist: polars; extra == 'notebooks'
Provides-Extra: test
Requires-Dist: pytest; extra == 'test'
Requires-Dist: pytest-cov>=6.1.1; extra == 'test'
